README.md
src/xwsystem_wrapper.py
xwsystem-0.1.0.1.dist-info/METADATA
xwsystem-0.1.0.1.dist-info/WHEEL
xwsystem-0.1.0.1.dist-info/licenses/LICENSE
xwsystem-0.1.0.1.dist-info/RECORD
