Metadata-Version: 2.4
Name: xwsystem
Version: 0.1.0.1
Summary: Convenience wrapper for exonware-xwsystem - provides 'import xwsystem' alias
Project-URL: Homepage, https://exonware.com
Project-URL: Repository, https://github.com/exonware/xwsystem
Project-URL: Documentation, https://github.com/exonware/xwsystem#readme
Author-email: "Eng. Muhammad AlShehri" <connect@exonware.com>
License: MIT
License-File: LICENSE
Keywords: ai-optimization,bson,cbor,circuit-breaker,crypto,enterprise,exonware,framework,json,memory-management,monitoring,msgpack,object-pool,performance,security,serialization,threading,yaml
Classifier: Development Status :: 4 - Beta
Classifier: Intended Audience :: Developers
Classifier: Intended Audience :: Information Technology
Classifier: Intended Audience :: System Administrators
Classifier: License :: OSI Approved :: MIT License
Classifier: Operating System :: OS Independent
Classifier: Programming Language :: Python :: 3
Classifier: Programming Language :: Python :: 3.12
Classifier: Topic :: Database
Classifier: Topic :: Internet :: WWW/HTTP
Classifier: Topic :: Security :: Cryptography
Classifier: Topic :: Software Development :: Libraries :: Python Modules
Classifier: Topic :: System :: Monitoring
Classifier: Topic :: System :: Systems Administration
Requires-Python: >=3.12
Requires-Dist: exonware-xwsystem
Provides-Extra: full
Requires-Dist: exonware-xwsystem[full]; extra == 'full'
